aolney_jupyterlab_metadata_html_extension/__init__.py
aolney_jupyterlab_metadata_html_extension/_version.py
aolney_jupyterlab_metadata_html_extension-0.1.2.data/data/share/jupyter/labextensions/@aolney/jupyterlab-metadata-html-extension/package.json
aolney_jupyterlab_metadata_html_extension-0.1.2.data/data/share/jupyter/labextensions/@aolney/jupyterlab-metadata-html-extension/static/509.33351268ef3453229452.js
aolney_jupyterlab_metadata_html_extension-0.1.2.data/data/share/jupyter/labextensions/@aolney/jupyterlab-metadata-html-extension/static/728.4ca3836793d442ab8304.js
aolney_jupyterlab_metadata_html_extension-0.1.2.data/data/share/jupyter/labextensions/@aolney/jupyterlab-metadata-html-extension/static/remoteEntry.39f0a5ba49435aa0de16.js
aolney_jupyterlab_metadata_html_extension-0.1.2.data/data/share/jupyter/labextensions/@aolney/jupyterlab-metadata-html-extension/static/style.js
aolney_jupyterlab_metadata_html_extension-0.1.2.data/data/share/jupyter/labextensions/@aolney/jupyterlab-metadata-html-extension/static/third-party-licenses.json
aolney_jupyterlab_metadata_html_extension-0.1.2.data/data/share/jupyter/labextensions/@aolney/jupyterlab-metadata-html-extension/install.json
aolney_jupyterlab_metadata_html_extension-0.1.2.dist-info/METADATA
aolney_jupyterlab_metadata_html_extension-0.1.2.dist-info/WHEEL
aolney_jupyterlab_metadata_html_extension-0.1.2.dist-info/licenses/LICENSE
aolney_jupyterlab_metadata_html_extension-0.1.2.dist-info/RECORD
