Metadata-Version: 2.3
Name: aolney_jupyterlab_metadata_html_extension
Version: 0.1.2
Summary: A JupyterLab extension that uses cell metadata to define html that is injected into markdown cells.
Project-URL: Homepage, https://github.com/aolney/jupyterlab-metadata-html-extension
Project-URL: Bug Tracker, https://github.com/aolney/jupyterlab-metadata-html-extension/issues
Project-URL: Repository, https://github.com/aolney/jupyterlab-metadata-html-extension.git
Author-email: "Andrew M. Olney" <aolney@memphis.edu>
License:                                  Apache License
Keywords: jupyter,jupyterlab,jupyterlab-extension
Classifier: Framework :: Jupyter
Classifier: Framework :: Jupyter :: JupyterLab
Classifier: Framework :: Jupyter :: JupyterLab :: 4
Classifier: Framework :: Jupyter :: JupyterLab :: Extensions
Classifier: Framework :: Jupyter :: JupyterLab :: Extensions :: Prebuilt
Classifier: License :: OSI Approved :: BSD License
Classifier: Programming Language :: Python
Classifier: Programming Language :: Python :: 3
Classifier: Programming Language :: Python :: 3.8
Classifier: Programming Language :: Python :: 3.9
Classifier: Programming Language :: Python :: 3.10
Classifier: Programming Language :: Python :: 3.11
Classifier: Programming Language :: Python :: 3.12
Requires-Python: >=3.8
